tf2xgb/__init__.py
tf2xgb/_version.py
tf2xgb/tf2xgb.py
tf2xgb/utils.py
tf2xgb-0.1.0.dist-info/LICENSE
tf2xgb-0.1.0.dist-info/METADATA
tf2xgb-0.1.0.dist-info/WHEEL
tf2xgb-0.1.0.dist-info/top_level.txt
tf2xgb-0.1.0.dist-info/RECORD
